odoo/addons/website_sale_product_image_sample/README.rst
odoo/addons/website_sale_product_image_sample/__init__.py
odoo/addons/website_sale_product_image_sample/__manifest__.py
odoo/addons/website_sale_product_image_sample/i18n/es.po
odoo/addons/website_sale_product_image_sample/i18n/it.po
odoo/addons/website_sale_product_image_sample/i18n/website_sale_product_image_sample.pot
odoo/addons/website_sale_product_image_sample/models/__init__.py
odoo/addons/website_sale_product_image_sample/models/product_attribute.py
odoo/addons/website_sale_product_image_sample/models/product_template.py
odoo/addons/website_sale_product_image_sample/readme/CONTRIBUTORS.rst
odoo/addons/website_sale_product_image_sample/readme/DESCRIPTION.rst
odoo/addons/website_sale_product_image_sample/readme/ROADMAP.rst
odoo/addons/website_sale_product_image_sample/readme/USAGE.rst
odoo/addons/website_sale_product_image_sample/static/description/icon.png
odoo/addons/website_sale_product_image_sample/static/description/index.html
odoo/addons/website_sale_product_image_sample/static/img/image.gif
odoo/addons/website_sale_product_image_sample/static/src/css/product_configurator.scss
odoo/addons/website_sale_product_image_sample/views/variants.xml
odoo_addon_website_sale_product_image_sample-16.0.1.0.0.7.dist-info/METADATA
odoo_addon_website_sale_product_image_sample-16.0.1.0.0.7.dist-info/WHEEL
odoo_addon_website_sale_product_image_sample-16.0.1.0.0.7.dist-info/top_level.txt
odoo_addon_website_sale_product_image_sample-16.0.1.0.0.7.dist-info/RECORD
