Metadata-Version: 2.1
Name: odoo-addon-website-sale-product-image-sample
Version: 16.0.1.0.0.7
Summary: Display product image sample to select product variant on website
Home-page: https://github.com/OCA/e-commerce
Author: Xtendoo, Odoo Community Association (OCA)
Author-email: support@odoo-community.org
License: LGPL-3
Platform: UNKNOWN
Classifier: Programming Language :: Python
Classifier: Framework :: Odoo
Classifier: Framework :: Odoo :: 16.0
Classifier: License :: OSI Approved :: GNU Lesser General Public License v3 (LGPLv3)
Classifier: Development Status :: 5 - Production/Stable
Requires-Python: >=3.10
Requires-Dist: odoo <16.1dev,>=16.0a
